jybmiTest/bmi.py
jybmiTest/currentPage.py
jybmiTest-0.0.0.1.dist-info/METADATA
jybmiTest-0.0.0.1.dist-info/WHEEL
jybmiTest-0.0.0.1.dist-info/top_level.txt
jybmiTest-0.0.0.1.dist-info/RECORD
