Metadata-Version: 2.1
Name: jybmiTest
Version: 0.0.0.1
Summary: My First Test Package
Home-page: UNKNOWN
Author: Jooyoung Kim
Author-email: jooy711@naver.com
License: MIT
Platform: UNKNOWN
Requires-Python: >=3
